LICENSE
MANIFEST.in
README.rst
setup.py
bin/calflate
calflate/__init__.py
calflate/__main__.py
calflate.egg-info/PKG-INFO
calflate.egg-info/SOURCES.txt
calflate.egg-info/dependency_links.txt
calflate.egg-info/top_level.txt