Metadata-Version: 1.1
Name: calflate
Version: 0.4.1
Summary: import external CalDAV and CardDAV entries
Home-page: https://github.com/chripo/calflate/
Author: Christoph Polcin
Author-email: labs@polcin.de
License: BSD revised
Download-URL: https://github.com/chripo/calflate/tarball/0.4.1
Keywords: calendar,addressbook,CalDAV,CardDAV
Platform: Any
Classifier: Development Status :: 4 - Beta
Classifier: Environment :: Console
Classifier: Operating System :: OS Independent
Classifier: Programming Language :: Python
Classifier: Programming Language :: Python :: 2
Classifier: Programming Language :: Python :: 2.6
Classifier: Programming Language :: Python :: 2.7
Provides: calflate
